xctools_mcp_server.py
xctools_mcp_server-0.1.0.dist-info/licenses/LICENSE
xctools_mcp_server-0.1.0.dist-info/METADATA
xctools_mcp_server-0.1.0.dist-info/WHEEL
xctools_mcp_server-0.1.0.dist-info/entry_points.txt
xctools_mcp_server-0.1.0.dist-info/top_level.txt
xctools_mcp_server-0.1.0.dist-info/RECORD
