Metadata-Version: 2.4
Name: xctools-mcp-server
Version: 0.1.0
Summary: A Model Context Protocol server for different Xcode related tools
Requires-Python: >=3.13
License-File: LICENSE
Requires-Dist: mcp[cli]>=1.2.0
Dynamic: license-file
